AUTHORS
CHANGELOG
FAQ
LICENSE
MANIFEST.in
NEWS
README
THANKS
setup.cfg
setup.py
doc/Makefile
doc/source/conf.py
doc/source/index.rst
doc/source/io.rst
doc/source/misc.rst
doc/source/randomness.rst
doc/source/sorting.rst
doc/source/todo.rst
doc/source/generated/ion.cycle.rst
doc/source/generated/ion.min_nbits.rst
doc/source/generated/ion.notional_nbits.rst
doc/source/generated/ion.order.rst
doc/source/generated/ion.piz.rst
doc/source/generated/ion.read_everyline.rst
doc/source/generated/ion.read_everything.rst
doc/source/generated/ion.setattrs.rst
doc/source/generated/ion.tupled.rst
doc/sphinxext/LICENSE.txt
doc/sphinxext/__init__.py
doc/sphinxext/autosummary.py
doc/sphinxext/autosummary_generate.py
doc/sphinxext/docscrape.py
doc/sphinxext/docscrape_sphinx.py
doc/sphinxext/numpydoc.py
doc/sphinxext/plot_directive.py
examples/damagecontinuity-sample-plot.svg
examples/damagecontinuity.rst
examples/num_exclusions.py
examples/ohritem.py
ion/__init__.py
ion/color.py
ion/cpercep.py
ion/functional.py
ion/io.py
ion/metadata.py
ion/sort.py
ion/n/__init__.py
ion/n/bitvec.py
ion/n/coord.py
ion/n/powers.py
ion/n/random.py
ion/xn/curve.py
ion/xn/fixed.py
ion/xn/spline.py
pyion.egg-info/PKG-INFO
pyion.egg-info/SOURCES.txt
pyion.egg-info/dependency_links.txt
pyion.egg-info/entry_points.txt
pyion.egg-info/top_level.txt
pyion.egg-info/zip-safe
tests/iontest.py
tests/test_number.py
tests/n/iontest.py
tests/n/test_limits.py
tests/xn/fixed_test.py