Metadata-Version: 1.0
Name: pyion
Version: 0.02dev
Summary: Core modules by Ion
Home-page: http://repo.or.cz/w/pyion.git
Author: David Gowers
Author-email: 00ai99@gmail.com
License: GPLv3
Download-URL: http://repo.or.cz/pyion.git
Keywords: file math random miscellaneous
Platform: UNKNOWN
Classifier: Development Status :: 4 - Beta
Classifier: Intended Audience :: Developers
Classifier: License :: OSI Approved :: GNU General Public License (GPL)
Classifier: Programming Language :: Python :: 2.5
Classifier: Topic :: Software Development :: Libraries :: Python Modules
